fa_singer_io/__init__.py
fa_singer_io/py.typed
fa_singer_io/time.py
fa_singer_io/json_schema/__init__.py
fa_singer_io/json_schema/_factory.py
fa_singer_io/json_schema/_inner.py
fa_singer_io/json_schema/core.py
fa_singer_io/json_schema/factory.py
fa_singer_io/singer/__init__.py
fa_singer_io/singer/_utils.py
fa_singer_io/singer/deserializer.py
fa_singer_io/singer/emitter.py
fa_singer_io/singer/encoder.py
fa_singer_io/singer/errors.py
fa_singer_io/singer/validate.py
fa_singer_io/singer/record/__init__.py
fa_singer_io/singer/record/core.py
fa_singer_io/singer/record/decoder.py
fa_singer_io/singer/record/encode.py
fa_singer_io/singer/record/factory.py
fa_singer_io/singer/schema/__init__.py
fa_singer_io/singer/schema/core.py
fa_singer_io/singer/schema/decoder.py
fa_singer_io/singer/schema/encode.py
fa_singer_io/singer/schema/factory.py
fa_singer_io/singer/state/__init__.py
fa_singer_io/singer/state/core.py
fa_singer_io/singer/state/decoder.py
fa_singer_io/singer/state/encode.py
fa_singer_io-3.0.0.dist-info/WHEEL
fa_singer_io-3.0.0.dist-info/METADATA
fa_singer_io-3.0.0.dist-info/RECORD
