Metadata-Version: 2.4
Name: fa_singer_io
Version: 3.0.0
Summary: Singer io SDK with strict types
Author-email: Product Team <development@fluidattacks.com>
Requires-Python: >=3.11
Classifier: License :: OSI Approved :: MIT License
Requires-Dist: fa-purity >=2.5.0, <3.0.0
Requires-Dist: Deprecated >=1.2.18, <2.0.0
Requires-Dist: jsonschema >=4.23.0, <5.0.0
Requires-Dist: types-jsonschema >=4.23.0.20250516, <5.0.0
Requires-Dist: pyRFC3339 >=2.0.1, <3.0.0
